cartesian/__init__.py
cartesian/algorithm.py
cartesian/cgp.py
cartesian/sklearn_api.py
cartesian/util.py
cartesian-0.1.10.dist-info/METADATA
cartesian-0.1.10.dist-info/RECORD
cartesian-0.1.10.dist-info/WHEEL
cartesian-0.1.10.dist-info/top_level.txt
