Metadata-Version: 2.1
Name: cartesian
Version: 0.1.10
Summary: Minimal cartesian genetic programming for symbolic regression.
Home-page: https://github.com/ohjeah/cartesian
Author: Markus Quade
Author-email: info@markusqua.de
License: MIT
Platform: UNKNOWN
Classifier: Programming Language :: Python
Classifier: Programming Language :: Python :: 3.6
Classifier: Development Status :: 4 - Beta
Classifier: Intended Audience :: Science/Research
Classifier: License :: OSI Approved :: MIT License
Classifier: Topic :: Scientific/Engineering :: Mathematics
Requires-Python: >=3.6
Requires-Dist: scikit-learn[alldeps]
Requires-Dist: joblib
Requires-Dist: scipy
Requires-Dist: numpy
Requires-Dist: dataclasses
